setup.py
hkshiteshpkg/__init__.py
hkshiteshpkg/calculator.py
hkshiteshpkgnew.egg-info/PKG-INFO
hkshiteshpkgnew.egg-info/SOURCES.txt
hkshiteshpkgnew.egg-info/dependency_links.txt
hkshiteshpkgnew.egg-info/top_level.txt